kapoorlabs_lightning/__init__.py
kapoorlabs_lightning/_version.py
kapoorlabs_lightning/caped.yaml
kapoorlabs_lightning/graph_functions.py
kapoorlabs_lightning/kapoorlabs.yaml
kapoorlabs_lightning/lightning_trainer.py
kapoorlabs_lightning/metrics.py
kapoorlabs_lightning/optimizers.py
kapoorlabs_lightning/pytorch_callbacks.py
kapoorlabs_lightning/pytorch_datasets.py
kapoorlabs_lightning/pytorch_loggers.py
kapoorlabs_lightning/pytorch_losses.py
kapoorlabs_lightning/pytorch_models.py
kapoorlabs_lightning/pytorch_transforms.py
kapoorlabs_lightning/schedulers.py
kapoorlabs_lightning/utils.py
kapoorlabs_lightning/_tests/__init__.py
kapoorlabs_lightning/_tests/test_pytorch_models.py
kapoorlabs_lightning-5.6.2.dist-info/licenses/LICENSE
kapoorlabs_lightning-5.6.2.dist-info/METADATA
kapoorlabs_lightning-5.6.2.dist-info/WHEEL
kapoorlabs_lightning-5.6.2.dist-info/top_level.txt
kapoorlabs_lightning-5.6.2.dist-info/RECORD
