Metadata-Version: 2.4
Name: KapoorLabs-Lightning
Version: 5.6.2
Summary: Lightning modules for KapoorLabs specific projects
Home-page: https://github.com/Kapoorlabs-CAPED/KapoorLabs-Lightning
Author: Varun Kapoor, Mari Tolonen, Jakub Sedzinski
Author-email: randomaccessiblekapoor@gmail.com
License: BSD-3-Clause
Project-URL: Bug Tracker, https://github.com/Kapoorlabs-CAPED/KapoorLabs-Lightning/issues
Project-URL: Documentation, https://github.com/Kapoorlabs-CAPED/KapoorLabs-Lightning#README.md
Project-URL: Source Code, https://github.com/Kapoorlabs-CAPED/KapoorLabs-Lightning
Project-URL: User Support, https://github.com/Kapoorlabs-CAPED/KapoorLabs-Lightning/issues
Classifier: Development Status :: 5 - Production/Stable
Classifier: Intended Audience :: Developers
Classifier: License :: OSI Approved :: BSD License
Classifier: Operating System :: OS Independent
Classifier: Programming Language :: Python
Classifier: Programming Language :: Python :: 3
Classifier: Programming Language :: Python :: 3 :: Only
Classifier: Programming Language :: Python :: 3.8
Classifier: Programming Language :: Python :: 3.9
Classifier: Programming Language :: Python :: 3.10
Classifier: Topic :: Scientific/Engineering :: Image Processing
Requires-Python: >=3.8
License-File: LICENSE
Requires-Dist: numpy
Requires-Dist: torch
Requires-Dist: torchvision
Requires-Dist: lightning
Requires-Dist: h5py
Requires-Dist: rich
Requires-Dist: tox
Requires-Dist: pytest-cov
Requires-Dist: pyntcloud
Requires-Dist: trackastra
Provides-Extra: testing
Requires-Dist: tox; extra == "testing"
Requires-Dist: pytest; extra == "testing"
Requires-Dist: pytest-cov; extra == "testing"
Dynamic: license-file
